{
  "publicPath": "/_nuxt/",
  "all": [
    "../server/index.spa.html",
    "../server/index.ssr.html",
    "311a2d4d599f7e5bd790.js",
    "32ded5284d79f4a35aad.js",
    "4187cdb5398fac9d25e2.js",
    "41dccc96d2d7a4fd1668.js",
    "4e4d0387b71b4539c23b.js",
    "5407908505dbb02560d9.js",
    "560418cb4ead47a50d1e.js",
    "5c35d50e9d12c2981651.js",
    "62bcf57db8e17331dc63.js",
    "6f968b45647b6e02592b.js",
    "7b83f8f0816d35e415de.js",
    "8cd23b5b8c49f27bb6eb.js",
    "8d706debddaf91c0a0e0.js",
    "8f4585846ca3b6117762.js",
    "904bf52b613d7359f3f6.js",
    "99237e4ac0fae07266f0.js",
    "LICENSES",
    "a8a28637501f4f351239.js",
    "cfb56d17c63f08d6ea3e.js",
    "d1dab072b03d17a303e2.js",
    "d269f45e02ab5a7ccae6.js",
    "f0300d3cb3f5e5f98bcc.js",
    "f8649136fdec279fde4a.js",
    "fcd9def8c6eacbe703b3.js",
    "fe7b3f56b0d0d23ea531.js",
    "fonts/535877f.woff",
    "fonts/732389d.ttf",
    "img/09383ba.jpg",
    "img/741e763.jpg",
    "img/766c2a3.jpg",
    "img/836e20d.png",
    "img/b0d58bb.svg",
    "img/d3936ae.jpg",
    "manifest.306e7eea.json"
  ],
  "initial": [
    "62bcf57db8e17331dc63.js",
    "d1dab072b03d17a303e2.js",
    "cfb56d17c63f08d6ea3e.js",
    "4e4d0387b71b4539c23b.js"
  ],
  "async": [
    "311a2d4d599f7e5bd790.js",
    "32ded5284d79f4a35aad.js",
    "4187cdb5398fac9d25e2.js",
    "41dccc96d2d7a4fd1668.js",
    "5407908505dbb02560d9.js",
    "560418cb4ead47a50d1e.js",
    "5c35d50e9d12c2981651.js",
    "6f968b45647b6e02592b.js",
    "7b83f8f0816d35e415de.js",
    "8cd23b5b8c49f27bb6eb.js",
    "8d706debddaf91c0a0e0.js",
    "8f4585846ca3b6117762.js",
    "904bf52b613d7359f3f6.js",
    "99237e4ac0fae07266f0.js",
    "a8a28637501f4f351239.js",
    "d269f45e02ab5a7ccae6.js",
    "f0300d3cb3f5e5f98bcc.js",
    "f8649136fdec279fde4a.js",
    "fcd9def8c6eacbe703b3.js",
    "fe7b3f56b0d0d23ea531.js"
  ],
  "modules": {
    "13518080": [
      21
    ],
    "16702912": [
      20,
      27,
      28
    ],
    "20501034": [
      19
    ],
    "22091226": [
      20,
      27,
      28
    ],
    "24122063": [
      19
    ],
    "26971992": [
      12
    ],
    "27341195": [
      6,
      29,
      33,
      33
    ],
    "33674282": [
      6,
      29,
      33,
      33
    ],
    "38920696": [
      26
    ],
    "45385970": [
      21
    ],
    "48308118": [
      23
    ],
    "48773085": [
      21
    ],
    "49157724": [
      6,
      29,
      33,
      33
    ],
    "51418407": [
      19
    ],
    "51536550": [
      4,
      32,
      34,
      31,
      30
    ],
    "55963920": [
      19
    ],
    "57412147": [
      21
    ],
    "57460606": [
      6,
      29,
      33,
      33
    ],
    "62430860": [
      21
    ],
    "65192044": [
      9
    ],
    "68385331": [
      19
    ],
    "75843808": [
      20,
      27,
      28
    ],
    "78699361": [
      21
    ],
    "79346284": [
      19
    ],
    "1a0a892c": [
      20,
      27,
      28
    ],
    "0f1e562c": [
      21
    ],
    "13f9a2c1": [
      20,
      27,
      28
    ],
    "44e32a10": [
      6,
      29,
      33,
      33
    ],
    "459bbf43": [
      20,
      27,
      28
    ],
    "1335d6aa": [
      20,
      27,
      28
    ],
    "77bcaa0e": [
      20,
      27,
      28
    ],
    "3e0fa4b1": [
      21
    ],
    "9ebc7d6a": [
      21
    ],
    "6630ea1d": [
      20,
      27,
      28
    ],
    "3a808482": [
      21
    ],
    "24c7d128": [
      20,
      27,
      28
    ],
    "7fd8bec1": [
      21
    ],
    "7b5d5906": [
      21
    ],
    "e8d3f36a": [
      21
    ],
    "8d876902": [
      20,
      27,
      28
    ],
    "775cbd09": [
      20,
      27,
      28
    ],
    "505a3c31": [
      20,
      27,
      28
    ],
    "6ac68cf2": [
      20,
      27,
      28
    ],
    "166c8989": [
      20,
      27,
      28
    ],
    "89fd425e": [
      21
    ],
    "af7bf89a": [
      21
    ],
    "4e0ec488": [
      21
    ],
    "15e089b7": [
      20,
      27,
      28
    ],
    "560ae9c0": [
      20,
      27,
      28
    ],
    "2fe04f05": [
      20,
      27,
      28
    ],
    "e1e6b156": [
      21
    ],
    "4fee87ed": [
      21
    ],
    "fc332de0": [
      21
    ],
    "06893d66": [
      21
    ],
    "176ab594": [
      20,
      27,
      28
    ],
    "fe76a120": [
      21
    ],
    "de07dbf6": [
      20,
      27,
      28
    ],
    "4b3f0de1": [
      20,
      27,
      28
    ],
    "6c697a06": [
      21
    ],
    "0aa0abd5": [
      21
    ],
    "9ccaa1f0": [
      21
    ],
    "f7e8a4d4": [
      21
    ],
    "43b6b5b0": [
      20,
      27,
      28
    ],
    "2d8f77a2": [
      20,
      27,
      28
    ],
    "075bac79": [
      20,
      27,
      28
    ],
    "4d51367e": [
      20,
      27,
      28
    ],
    "74daa32c": [
      21
    ],
    "1bca6cbb": [
      20,
      27,
      28
    ],
    "2007124f": [
      6,
      29,
      33,
      33
    ],
    "1b1934e4": [
      6,
      29,
      33,
      33
    ],
    "f2f6a3d4": [
      6,
      29,
      33,
      33
    ],
    "00bb4780": [
      6,
      29,
      33,
      33
    ],
    "12ffc805": [
      6,
      29,
      33,
      33
    ],
    "d460ed80": [
      6,
      29,
      33,
      33
    ],
    "7fac13e0": [
      6,
      29,
      33,
      33
    ],
    "2e13a006": [
      6,
      29,
      33,
      33
    ],
    "1b58c5d3": [
      6,
      29,
      33,
      33
    ],
    "09e247aa": [
      6,
      29,
      33,
      33
    ],
    "50a9cf67": [
      6,
      29,
      33,
      33
    ],
    "256c2652": [
      6,
      29,
      33,
      33
    ],
    "d4ebe978": [
      6,
      29,
      33,
      33
    ],
    "65140eac": [
      6,
      29,
      33,
      33
    ],
    "564a22c8": [
      6,
      29,
      33,
      33
    ],
    "873e6746": [
      6,
      29,
      33,
      33
    ],
    "17344e88": [
      6,
      29,
      33,
      33
    ],
    "0c60d9cc": [
      6,
      29,
      33,
      33
    ],
    "16d34974": [
      6,
      29,
      33,
      33
    ],
    "68ee5860": [
      6,
      29,
      33,
      33
    ],
    "c5e3f390": [
      6,
      29,
      33,
      33
    ],
    "466f7726": [
      6,
      29,
      33,
      33
    ],
    "62f31baf": [
      6,
      29,
      33,
      33
    ],
    "18ce9298": [
      6,
      29,
      33,
      33
    ],
    "13dd9ac4": [
      6,
      29,
      33,
      33
    ],
    "3cba42b6": [
      6,
      29,
      33,
      33
    ],
    "49a16b70": [
      6,
      29,
      33,
      33
    ],
    "3026b24f": [
      6,
      29,
      33,
      33
    ],
    "a4fedfe0": [
      6,
      29,
      33,
      33
    ],
    "47a69740": [
      6,
      29,
      33,
      33
    ],
    "8c36acd6": [
      6,
      29,
      33,
      33
    ],
    "1f2b2aab": [
      6,
      29,
      33,
      33
    ],
    "0078dfea": [
      6,
      29,
      33,
      33
    ],
    "be86b5fc": [
      6,
      29,
      33,
      33
    ],
    "7413560a": [
      6,
      29,
      33,
      33
    ],
    "26cd636e": [
      6,
      29,
      33,
      33
    ],
    "36e37d36": [
      6,
      29,
      33,
      33
    ],
    "6f081b02": [
      6,
      29,
      33,
      33
    ],
    "a1695974": [
      6,
      29,
      33,
      33
    ],
    "75cc0136": [
      6,
      29,
      33,
      33
    ],
    "53b02f24": [
      6,
      29,
      33,
      33
    ],
    "715345a4": [
      6,
      29,
      33,
      33
    ],
    "182d34dc": [
      6,
      29,
      33,
      33
    ],
    "47320f8e": [
      6,
      29,
      33,
      33
    ],
    "5f6b89d4": [
      6,
      29,
      33,
      33
    ],
    "fea4ecc8": [
      6,
      29,
      33,
      33
    ],
    "9ff1587c": [
      6,
      29,
      33,
      33
    ],
    "49f44c8a": [
      6,
      29,
      33,
      33
    ],
    "d733f094": [
      6,
      29,
      33,
      33
    ],
    "6b34df30": [
      6,
      29,
      33,
      33
    ],
    "028bfef2": [
      6,
      29,
      33,
      33
    ],
    "69d7faa2": [
      21
    ],
    "457d29e2": [
      21
    ],
    "45f3fc02": [
      21
    ],
    "8ac3bed6": [
      21
    ],
    "3f395a93": [
      20,
      27,
      28
    ],
    "d307b620": [
      21
    ],
    "3c65b36e": [
      21
    ],
    "9b313284": [
      20,
      27,
      28
    ],
    "a2883fdc": [
      21
    ],
    "68a2339c": [
      21
    ],
    "01a0d6d2": [
      20,
      27,
      28
    ],
    "1fa0c414": [
      20,
      27,
      28
    ],
    "4e4a194e": [
      20,
      27,
      28
    ],
    "08ad0534": [
      20,
      27,
      28
    ],
    "67f86643": [
      20,
      27,
      28
    ],
    "056cf212": [
      21
    ],
    "71c8cda1": [
      21
    ],
    "e2996be0": [
      21
    ],
    "73fe3070": [
      21
    ],
    "8ee07a54": [
      21
    ],
    "7f4fe5c8": [
      21
    ],
    "2183e97c": [
      21
    ],
    "fa706012": [
      21
    ],
    "2ddd86d8": [
      20,
      27,
      28
    ],
    "39cf4a86": [
      20,
      27,
      28
    ],
    "8826e808": [
      21
    ],
    "a4a76c7a": [
      20,
      27,
      28
    ],
    "519a8f04": [
      20,
      27,
      28
    ],
    "2b3a842e": [
      20,
      27,
      28
    ],
    "e1fc237a": [
      21
    ],
    "9aac01ce": [
      21
    ],
    "236173aa": [
      6,
      29,
      33,
      33
    ],
    "1e078950": [
      21
    ],
    "e7699ca2": [
      21
    ],
    "0f1ad1e1": [
      21
    ],
    "a5d5e10c": [
      21
    ],
    "2e5df3a5": [
      21
    ],
    "977328f4": [
      21
    ],
    "89da114e": [
      21
    ],
    "1da3e698": [
      21
    ],
    "290480fe": [
      21
    ],
    "09f24055": [
      21
    ],
    "6fc65579": [
      21
    ],
    "fb177004": [
      21
    ],
    "2b88e4ce": [
      21
    ],
    "0acb2dc0": [
      21
    ],
    "1a0f45ca": [
      21
    ],
    "5bc6bb29": [
      20,
      27,
      28
    ],
    "affb01e2": [
      6,
      29,
      33,
      33
    ],
    "7487a27a": [
      6,
      29,
      33,
      33
    ],
    "71a5fbaa": [
      6,
      29,
      33,
      33
    ],
    "049842ae": [
      6,
      29,
      33,
      33
    ],
    "6a4d7749": [
      6,
      29,
      33,
      33
    ],
    "02f75796": [
      21
    ],
    "2618a554": [
      21
    ],
    "0a7446bf": [
      21
    ],
    "1b2b9625": [
      21
    ],
    "7afea8f3": [
      21
    ],
    "02f99d71": [
      21
    ],
    "a7fe3ff4": [
      21
    ],
    "6fb93c2a": [
      21
    ],
    "c3e636ca": [
      21
    ],
    "4cd0e932": [
      21
    ],
    "4297fd23": [
      21
    ],
    "70368ed2": [
      20,
      27,
      28
    ],
    "2df8d884": [
      20,
      27,
      28
    ],
    "1712aef6": [
      20,
      27,
      28
    ],
    "49a0db28": [
      20,
      27,
      28
    ],
    "9ba35dc2": [
      20,
      27,
      28
    ],
    "69ad3812": [
      21
    ],
    "752f798d": [
      21
    ],
    "6e338a74": [
      21
    ],
    "ab9beb4a": [
      21
    ],
    "7f3b1e26": [
      21
    ],
    "5ed937da": [
      21
    ],
    "d265ddfa": [
      6,
      29,
      33,
      33
    ],
    "ee6a68e2": [
      6,
      29,
      33,
      33
    ],
    "79a94f32": [
      6,
      29,
      33,
      33
    ],
    "ebe25220": [
      6,
      29,
      33,
      33
    ],
    "62fb8040": [
      6,
      29,
      33,
      33
    ],
    "070a93c0": [
      6,
      29,
      33,
      33
    ],
    "19a75823": [
      6,
      29,
      33,
      33
    ],
    "94c91afa": [
      6,
      29,
      33,
      33
    ],
    "77541e58": [
      20,
      27,
      28
    ],
    "05bd9042": [
      20,
      27,
      28
    ],
    "4ba9798e": [
      20,
      27,
      28
    ],
    "52ee78d4": [
      20,
      27,
      28
    ],
    "28f4f5a8": [
      20,
      27,
      28
    ],
    "aef7d05a": [
      6,
      29,
      33,
      33
    ],
    "55bbed9e": [
      21
    ],
    "2d1c474f": [
      21
    ],
    "02f2cbe0": [
      21
    ],
    "6ec17506": [
      21
    ],
    "61a5de6d": [
      21
    ],
    "730c0271": [
      21
    ],
    "2ad99763": [
      21
    ],
    "8a2ef056": [
      21
    ],
    "0a55fc21": [
      21
    ],
    "087eecfe": [
      21
    ],
    "e52095b0": [
      21
    ],
    "68eeaa41": [
      21
    ],
    "ad06505e": [
      20,
      27,
      28
    ],
    "1be9bfd6": [
      21
    ],
    "690c984a": [
      21
    ],
    "b310bad2": [
      20,
      27,
      28
    ],
    "749b5bc8": [
      20,
      27,
      28
    ],
    "5340147e": [
      20,
      27,
      28
    ],
    "5e7faa15": [
      20,
      27,
      28
    ],
    "7c0f7190": [
      20,
      27,
      28
    ],
    "111b26c4": [
      20,
      27,
      28
    ],
    "3c20ba39": [
      20,
      27,
      28
    ],
    "6132d358": [
      20,
      27,
      28
    ],
    "0871c83f": [
      20,
      27,
      28
    ],
    "c5d60c38": [
      20,
      27,
      28
    ],
    "86a86a38": [
      21
    ],
    "e9840bba": [
      21
    ],
    "e0a0b366": [
      21
    ],
    "b856d9a8": [
      21
    ],
    "147e3641": [
      21
    ],
    "4539a893": [
      21
    ],
    "4dbeabc6": [
      21
    ],
    "a9a77fc6": [
      21
    ],
    "1b854676": [
      21
    ],
    "6df15151": [
      21
    ],
    "dbe6f05e": [
      21
    ],
    "06231eba": [
      21
    ],
    "1dd44ecf": [
      21
    ],
    "4de7a29a": [
      20,
      27,
      28
    ],
    "6ea585c4": [
      20,
      27,
      28
    ],
    "bd1ec8a4": [
      20,
      27,
      28
    ],
    "dfa70c94": [
      20,
      27,
      28
    ],
    "0bd6410c": [
      20,
      27,
      28
    ],
    "02cb89a1": [
      20,
      27,
      28
    ],
    "c170720a": [
      6,
      29,
      33,
      33
    ],
    "014c6350": [
      20,
      27,
      28
    ],
    "7f5345c6": [
      6,
      29,
      33,
      33
    ],
    "20eaa4dc": [
      20,
      27,
      28
    ],
    "2a2d2158": [
      20,
      27,
      28
    ],
    "361da30b": [
      20,
      27,
      28
    ],
    "b5d42630": [
      20,
      27,
      28
    ],
    "62b2dbd8": [
      20,
      27,
      28
    ],
    "221f2638": [
      20,
      27,
      28
    ],
    "9e558b00": [
      21
    ],
    "f0554b3c": [
      21
    ],
    "097a7f0a": [
      21
    ],
    "5c5edc8a": [
      21
    ],
    "d74d4a8c": [
      21
    ],
    "ed0c0f26": [
      21
    ],
    "310afd1c": [
      21
    ],
    "50bcba25": [
      21
    ],
    "593b4cf9": [
      21
    ],
    "6afbf6fb": [
      21
    ],
    "41f0d012": [
      21
    ],
    "796f2b71": [
      21
    ],
    "3dc41714": [
      21
    ],
    "3201fb42": [
      21
    ],
    "9823ce42": [
      21
    ],
    "2d50118d": [
      21
    ],
    "418d534e": [
      21
    ],
    "6e0d02f4": [
      20,
      27,
      28
    ],
    "4753a820": [
      21
    ],
    "90c42b7c": [
      21
    ],
    "0063625c": [
      21
    ],
    "688786c4": [
      20,
      27,
      28
    ],
    "01614f20": [
      6,
      29,
      33,
      33
    ],
    "fa6436fe": [
      21
    ],
    "8ef182c6": [
      21
    ],
    "646e200d": [
      21
    ],
    "3eb37456": [
      21
    ],
    "5e1a53de": [
      21
    ],
    "7f7b796c": [
      21
    ],
    "37fff77e": [
      21
    ],
    "71386c77": [
      21
    ],
    "a433c8a2": [
      20,
      27,
      28
    ],
    "3687007e": [
      20,
      27,
      28
    ],
    "18bb7b32": [
      20,
      27,
      28
    ],
    "4171fa98": [
      20,
      27,
      28
    ],
    "461a1503": [
      20,
      27,
      28
    ],
    "2bc7feb8": [
      20,
      27,
      28
    ],
    "35c2ab2e": [
      20,
      27,
      28
    ],
    "321339f8": [
      20,
      27,
      28
    ],
    "2f1b4d98": [
      20,
      27,
      28
    ],
    "f8f783a8": [
      20,
      27,
      28
    ],
    "66ff1e6e": [
      20,
      27,
      28
    ],
    "55bd4b76": [
      20,
      27,
      28
    ],
    "340b737e": [
      21
    ],
    "7b779d51": [
      21
    ],
    "3c069bf0": [
      21
    ],
    "b48799e4": [
      21
    ],
    "60d958bc": [
      21
    ],
    "3c8bfd66": [
      21
    ],
    "22ffea6a": [
      21
    ],
    "16e9e22c": [
      21
    ],
    "a9ac0b7c": [
      21
    ],
    "4093b444": [
      20,
      27,
      28
    ],
    "44c3b812": [
      20,
      27,
      28
    ],
    "4411cdc7": [
      20,
      27,
      28
    ],
    "43f5b1da": [
      20,
      27,
      28
    ],
    "f6be7fe0": [
      20,
      27,
      28
    ],
    "d3200064": [
      21
    ],
    "1c985d65": [
      20,
      27,
      28
    ],
    "3f5fe9c9": [
      20,
      27,
      28
    ],
    "48680ee2": [
      20,
      27,
      28
    ],
    "60ea1ff4": [
      6,
      29,
      33,
      33
    ],
    "0cd727b3": [
      20,
      27,
      28
    ],
    "00749715": [
      20,
      27,
      28
    ],
    "3de2ef54": [
      20,
      27,
      28
    ],
    "99755b64": [
      21
    ],
    "791b52b7": [
      21
    ],
    "6d09311b": [
      21
    ],
    "55347ade": [
      21
    ],
    "718904d2": [
      21
    ],
    "4c0ac004": [
      21
    ],
    "22862e2d": [
      21
    ],
    "218536fc": [
      6,
      29,
      33,
      33
    ],
    "c0e11dbc": [
      6,
      29,
      33,
      33
    ],
    "03fa5b16": [
      21
    ],
    "044bbfd9": [
      21
    ],
    "d0208b6a": [
      21
    ],
    "0864873c": [
      21
    ],
    "c5e71aa8": [
      21
    ],
    "487f685f": [
      21
    ],
    "2a0ddf6c": [
      21
    ],
    "44c310c2": [
      21
    ],
    "60de6965": [
      21
    ],
    "61511a13": [
      21
    ],
    "30eb70ee": [
      21
    ],
    "9e98a420": [
      21
    ],
    "61e8a3a4": [
      21
    ],
    "608b4716": [
      21
    ],
    "683c3e09": [
      21
    ],
    "012851cc": [
      21
    ],
    "d595eebe": [
      21
    ],
    "2785a549": [
      21
    ],
    "32ade961": [
      21
    ],
    "5f87717c": [
      21
    ],
    "df75272a": [
      21
    ],
    "3c8f1ca6": [
      21
    ],
    "740c1fd8": [
      21
    ],
    "09c73c1e": [
      6,
      29,
      33,
      33
    ],
    "768f12e2": [
      20,
      27,
      28
    ],
    "063f3449": [
      21
    ],
    "41b9a200": [
      21
    ],
    "7a5cce91": [
      21
    ],
    "6860585a": [
      21
    ],
    "a127f53a": [
      21
    ],
    "324db8d0": [
      21
    ],
    "6f79a4a6": [
      21
    ],
    "5ef61d3a": [
      21
    ],
    "5fbd75d8": [
      21
    ],
    "12ed1c57": [
      6,
      29,
      33,
      33
    ],
    "eadebbbe": [
      6,
      29,
      33,
      33
    ],
    "7d1551e3": [
      6,
      29,
      33,
      33
    ],
    "cc22e5a6": [
      6,
      29,
      33,
      33
    ],
    "38dcc246": [
      20,
      27,
      28
    ],
    "475f6d30": [
      20,
      27,
      28
    ],
    "52d51a10": [
      20,
      27,
      28
    ],
    "02abfe6e": [
      20,
      27,
      28
    ],
    "6a5e4314": [
      20,
      27,
      28
    ],
    "5f7f2518": [
      20,
      27,
      28
    ],
    "9d19c67e": [
      20,
      27,
      28
    ],
    "9ae4ab42": [
      20,
      27,
      28
    ],
    "89437fce": [
      6,
      29,
      33,
      33
    ],
    "0c7982f9": [
      6,
      29,
      33,
      33
    ],
    "8e827b9a": [
      6,
      29,
      33,
      33
    ],
    "0fc860a2": [
      6,
      29,
      33,
      33
    ],
    "e3bda14c": [
      6,
      29,
      33,
      33
    ],
    "2a4548e6": [
      6,
      29,
      33,
      33
    ],
    "14966d44": [
      6,
      29,
      33,
      33
    ],
    "ad44ff5c": [
      6,
      29,
      33,
      33
    ],
    "b2553178": [
      6,
      29,
      33,
      33
    ],
    "288001d0": [
      6,
      29,
      33,
      33
    ],
    "0a111f6c": [
      6,
      29,
      33,
      33
    ],
    "7667e960": [
      6,
      29,
      33,
      33
    ],
    "aea323d8": [
      6,
      29,
      33,
      33
    ],
    "03842ea0": [
      6,
      29,
      33,
      33
    ],
    "a7026f62": [
      6,
      29,
      33,
      33
    ],
    "a73dcd7a": [
      6,
      29,
      33,
      33
    ],
    "369f5faf": [
      6,
      29,
      33,
      33
    ],
    "613faba3": [
      6,
      29,
      33,
      33
    ],
    "c7e640c2": [
      6,
      29,
      33,
      33
    ],
    "a753db0a": [
      6,
      29,
      33,
      33
    ],
    "8d560584": [
      6,
      29,
      33,
      33
    ],
    "32b81a57": [
      6,
      29,
      33,
      33
    ],
    "2be69d2b": [
      6,
      29,
      33,
      33
    ],
    "7efd481c": [
      6,
      29,
      33,
      33
    ],
    "77ea7f52": [
      6,
      29,
      33,
      33
    ],
    "59a152de": [
      21
    ],
    "5289f802": [
      21
    ],
    "9ab21ae4": [
      21
    ],
    "9545b3fa": [
      21
    ],
    "873903bc": [
      21
    ],
    "5b388b6b": [
      21
    ],
    "e702ba6a": [
      21
    ],
    "4cd8aa7c": [
      21
    ],
    "406584ab": [
      21
    ],
    "bb103dc2": [
      21
    ],
    "fb29707e": [
      21
    ],
    "ed610b7c": [
      21
    ],
    "68e7828d": [
      21
    ],
    "1442d2fe": [
      21
    ],
    "e299b46a": [
      21
    ],
    "2cb2fe0c": [
      21
    ],
    "3abb425c": [
      20,
      27,
      28
    ],
    "6a0882fe": [
      20,
      27,
      28
    ],
    "4cee52aa": [
      20,
      27,
      28
    ],
    "32c80153": [
      20,
      27,
      28
    ],
    "9a7d5d98": [
      20,
      27,
      28
    ],
    "0ba4a445": [
      20,
      27,
      28
    ],
    "0c789e5d": [
      20,
      27,
      28
    ],
    "0e0f2298": [
      20,
      27,
      28
    ],
    "39e4980a": [
      20,
      27,
      28
    ],
    "0325f6e5": [
      20,
      27,
      28
    ],
    "e01c9d88": [
      20,
      27,
      28
    ],
    "34247baa": [
      20,
      27,
      28
    ],
    "6db00aba": [
      20,
      27,
      28
    ],
    "7f01e1f7": [
      20,
      27,
      28
    ],
    "7fd10782": [
      20,
      27,
      28
    ],
    "38bdb918": [
      20,
      27,
      28
    ],
    "b4ff775a": [
      20,
      27,
      28
    ],
    "79c7123a": [
      20,
      27,
      28
    ],
    "2abab776": [
      20,
      27,
      28
    ],
    "753c731e": [
      20,
      27,
      28
    ],
    "1ce8b634": [
      20,
      27,
      28
    ],
    "80bf1da4": [
      20,
      27,
      28
    ],
    "0d7f2491": [
      20,
      27,
      28
    ],
    "0f00c531": [
      20,
      27,
      28
    ],
    "4a63e0f6": [
      20,
      27,
      28
    ],
    "3c0f8e27": [
      21
    ],
    "642cd582": [
      21
    ],
    "6127fcef": [
      21
    ],
    "73ac4f58": [
      21
    ],
    "47cd1959": [
      21
    ],
    "a585f00e": [
      21
    ],
    "45004fbe": [
      21
    ],
    "7f4578e8": [
      21
    ],
    "42f46e70": [
      20,
      27,
      28
    ],
    "8a0d9d1c": [
      21
    ],
    "1163ef67": [
      21
    ],
    "a7033af6": [
      21
    ],
    "4ac8121f": [
      21
    ],
    "6851d866": [
      21
    ],
    "4fe4ca80": [
      21
    ],
    "48691f42": [
      21
    ],
    "ae3a2624": [
      21
    ],
    "6080044f": [
      21
    ],
    "271da535": [
      21
    ],
    "160173fe": [
      20,
      27,
      28
    ],
    "54aca366": [
      21
    ],
    "e0fc34ce": [
      21
    ],
    "89c9a19a": [
      21
    ],
    "2a8c6df6": [
      21
    ],
    "52398f22": [
      21
    ],
    "784c7d6e": [
      21
    ],
    "a9b522e8": [
      21
    ],
    "0526d506": [
      21
    ],
    "4ea6bdc7": [
      21
    ],
    "78d3aa23": [
      21
    ],
    "dd133aba": [
      20,
      27,
      28
    ],
    "fd4e9a0c": [
      20,
      27,
      28
    ],
    "6edbf14c": [
      20,
      27,
      28
    ],
    "466ed928": [
      20,
      27,
      28
    ],
    "421d1a4e": [
      20,
      27,
      28
    ],
    "466bee6e": [
      20,
      27,
      28
    ],
    "e648cf78": [
      20,
      27,
      28
    ],
    "3d3da03c": [
      20,
      27,
      28
    ],
    "8c8d65dc": [
      20,
      27,
      28
    ],
    "4f0149aa": [
      20,
      27,
      28
    ],
    "f7ed569a": [
      20,
      27,
      28
    ],
    "2a77982c": [
      20,
      27,
      28
    ],
    "36851fdd": [
      20,
      27,
      28
    ],
    "4de52aff": [
      20,
      27,
      28
    ],
    "edf5043c": [
      20,
      27,
      28
    ],
    "d8401418": [
      20,
      27,
      28
    ],
    "4cbc681c": [
      20,
      27,
      28
    ],
    "73d6bc4b": [
      20,
      27,
      28
    ],
    "e30a53b6": [
      20,
      27,
      28
    ],
    "ff94cad8": [
      20,
      27,
      28
    ],
    "059a7b19": [
      20,
      27,
      28
    ],
    "19ab7e71": [
      20,
      27,
      28
    ],
    "413063ec": [
      20,
      27,
      28
    ],
    "3559374e": [
      20,
      27,
      28
    ],
    "415fb071": [
      20,
      27,
      28
    ],
    "1567014a": [
      20,
      27,
      28
    ],
    "039d301a": [
      20,
      27,
      28
    ],
    "657023e2": [
      20,
      27,
      28
    ],
    "6a64eb2c": [
      20,
      27,
      28
    ],
    "d183a01e": [
      20,
      27,
      28
    ],
    "670413d2": [
      20,
      27,
      28
    ],
    "697081ae": [
      20,
      27,
      28
    ],
    "bd690156": [
      20,
      27,
      28
    ],
    "0e1f748a": [
      19
    ],
    "b621273e": [
      19
    ],
    "20eb3b2c": [
      19
    ],
    "764fa2e0": [
      19
    ],
    "a9170498": [
      19
    ],
    "4a378c25": [
      19
    ],
    "8b56b81a": [
      19
    ],
    "45d33606": [
      19
    ],
    "9322a506": [
      19
    ],
    "f01c797a": [
      19
    ],
    "291a0c94": [
      2
    ],
    "232105cb": [
      13
    ],
    "003f415c": [
      23
    ],
    "3bca0961": [
      26
    ],
    "5def40de": [
      22
    ],
    "6cf6018a": [
      9
    ],
    "1cf8ea30": [
      14
    ],
    "67022eeb": [
      15,
      32
    ],
    "a3067fce": [
      5
    ],
    "7afb85cb": [
      8,
      32,
      30
    ],
    "bc35b6da": [
      19
    ],
    "51f02b01": [
      19
    ],
    "78d75ec0": [
      2
    ],
    "7c947db4": [
      2
    ],
    "72de57f7": [
      13
    ],
    "769b76eb": [
      13
    ],
    "b1f64708": [
      4,
      32,
      34,
      31,
      30
    ],
    "a013e320": [
      4,
      32,
      34,
      31,
      30
    ],
    "4f9db17e": [
      23
    ],
    "535ad072": [
      23
    ],
    "579dbc41": [
      26
    ],
    "520c4cbd": [
      22
    ],
    "7cac98b1": [
      22
    ],
    "3aaf072c": [
      9
    ],
    "e640d4a8": [
      19
    ],
    "59f3bb1c": [
      19
    ],
    "450f5f21": [
      19
    ],
    "f44c4b80": [
      19
    ],
    "1faecc8b": [
      19
    ],
    "d196d498": [
      19
    ],
    "0129dbe2": [
      19
    ],
    "46e365ed": [
      19
    ],
    "5ab52a07": [
      19
    ],
    "6f0c20e0": [
      19
    ],
    "ed3e5e96": [
      19
    ],
    "df9ec610": [
      19
    ],
    "4dfd1937": [
      19
    ],
    "63acb109": [
      19
    ],
    "4d932eea": [
      19
    ],
    "2b9f4c60": [
      19
    ],
    "0f232989": [
      19
    ],
    "5216b612": [
      19
    ],
    "68438e6d": [
      19
    ],
    "20f87d9a": [
      19
    ],
    "75c0631e": [
      19
    ],
    "10abe672": [
      19
    ],
    "fa70d17a": [
      19
    ],
    "3d333698": [
      19
    ],
    "3b7c8182": [
      19
    ],
    "6e074d4a": [
      19
    ],
    "4f0d6380": [
      19
    ],
    "2f161826": [
      19
    ],
    "baf63c76": [
      19
    ],
    "a386b7b2": [
      19
    ],
    "504122bb": [
      19
    ],
    "0a953b88": [
      19
    ],
    "b40787ee": [
      19
    ],
    "df2b7ef6": [
      19
    ],
    "43b2c82c": [
      19
    ],
    "1cb23231": [
      19
    ],
    "5379193e": [
      19
    ],
    "724e74a4": [
      19
    ],
    "5089a422": [
      19
    ],
    "520912f0": [
      19
    ],
    "5209fbae": [
      19
    ],
    "e08c44fc": [
      19
    ],
    "7e8f689f": [
      19
    ],
    "5d7d0729": [
      19
    ],
    "5240fc95": [
      19
    ],
    "524259b2": [
      19
    ],
    "240bc331": [
      19
    ],
    "68bb10ca": [
      19
    ],
    "0c48b53a": [
      19
    ],
    "7b6c2553": [
      19
    ],
    "194002f4": [
      19
    ],
    "39786b5e": [
      19
    ],
    "53b0bccc": [
      19
    ],
    "8d28c306": [
      19
    ],
    "53bed44d": [
      19
    ],
    "4a3729e8": [
      19
    ],
    "540549d2": [
      19
    ],
    "2e77b927": [
      19
    ],
    "42a50de4": [
      19
    ],
    "55df107a": [
      19
    ],
    "5546ac2f": [
      19
    ],
    "1221acff": [
      19
    ],
    "7d1c9314": [
      19
    ],
    "3cdace9e": [
      19
    ],
    "e9e4a604": [
      19
    ],
    "56d63e60": [
      19
    ],
    "ef450ef8": [
      19
    ],
    "0e18b0be": [
      19
    ],
    "65a3f2d5": [
      19
    ],
    "aa9705ce": [
      19
    ],
    "8cbf328c": [
      19
    ],
    "18560bc1": [
      19
    ],
    "23a12193": [
      19
    ],
    "8469ab4a": [
      19
    ],
    "58be008f": [
      19
    ],
    "5db393b1": [
      19
    ],
    "7aef2664": [
      19
    ],
    "248092f2": [
      19
    ],
    "1c7321cb": [
      19
    ],
    "40d0ec7e": [
      19
    ],
    "b3c5849e": [
      19
    ],
    "3bfca921": [
      19
    ],
    "3fa1449a": [
      19
    ],
    "5ac937b0": [
      19
    ],
    "bb650964": [
      19
    ],
    "00681391": [
      19
    ],
    "5dc636e8": [
      19
    ],
    "5b0e62e7": [
      19
    ],
    "5c346c31": [
      19
    ],
    "6709d4a3": [
      19
    ],
    "3299fda5": [
      19
    ],
    "49ddd3b7": [
      19
    ],
    "311009e8": [
      19
    ],
    "42711eab": [
      19
    ],
    "034fd71c": [
      19
    ],
    "14e1ad54": [
      19
    ],
    "3885c3f8": [
      19
    ],
    "84ca774a": [
      19
    ],
    "8fd82f38": [
      19
    ],
    "8d4ff60a": [
      19
    ],
    "8b48d640": [
      19
    ],
    "7da4cb82": [
      19
    ],
    "bda3f086": [
      19
    ],
    "599e10fc": [
      19
    ],
    "7315e4fc": [
      19
    ],
    "619ac8b0": [
      19
    ],
    "61b1f79d": [
      19
    ],
    "4a85436f": [
      19
    ],
    "71cbe451": [
      19
    ],
    "9b700568": [
      19
    ],
    "fd29f3c0": [
      19
    ],
    "628a5841": [
      19
    ],
    "5f1293a2": [
      19
    ],
    "0cad6099": [
      19
    ],
    "50b924b4": [
      19
    ],
    "e439886c": [
      19
    ],
    "3457c032": [
      19
    ],
    "21c107e6": [
      19
    ],
    "7431f50d": [
      19
    ],
    "6966a50a": [
      19
    ],
    "8d20a58a": [
      19
    ],
    "1e4d7a04": [
      19
    ],
    "647d0358": [
      19
    ],
    "3b7ef90a": [
      19
    ],
    "49475d0f": [
      19
    ],
    "3ffd9c29": [
      19
    ],
    "d2768988": [
      19
    ],
    "50284aa0": [
      19
    ],
    "1dd38321": [
      19
    ],
    "5e2e4fe3": [
      19
    ],
    "cb316184": [
      19
    ],
    "67d4fa1d": [
      19
    ],
    "c27d8662": [
      19
    ],
    "220c4f6e": [
      19
    ],
    "6ec0fba6": [
      19
    ],
    "159fe94c": [
      19
    ],
    "4d51abc2": [
      19
    ],
    "b9f12cf4": [
      19
    ],
    "79fcacae": [
      19
    ],
    "7fb06436": [
      19
    ],
    "32a31c1f": [
      19
    ],
    "2628da3d": [
      19
    ],
    "2411ac04": [
      19
    ],
    "69ce76c5": [
      19
    ],
    "670f8b54": [
      19
    ],
    "6b4665aa": [
      19
    ],
    "59e8602a": [
      19
    ],
    "4a84ee0c": [
      19
    ],
    "6bd7dc6a": [
      19
    ],
    "09afe566": [
      19
    ],
    "130ef6b5": [
      19
    ],
    "6c923c90": [
      19
    ],
    "41218fe2": [
      19
    ],
    "7592b4d4": [
      19
    ],
    "947f3576": [
      19
    ],
    "293d8269": [
      19
    ],
    "22727a36": [
      19
    ],
    "1f1da8de": [
      19
    ],
    "54e9d102": [
      19
    ],
    "6d382803": [
      19
    ],
    "6d6dcbcd": [
      19
    ],
    "6d708607": [
      19
    ],
    "453ff80b": [
      19
    ],
    "6329e368": [
      19
    ],
    "677b82a4": [
      19
    ],
    "298cb6f2": [
      19
    ],
    "ea86fd5e": [
      19
    ],
    "0ec6b422": [
      19
    ],
    "4bea1634": [
      19
    ],
    "62e17912": [
      19
    ],
    "6e45b812": [
      19
    ],
    "6e601598": [
      19
    ],
    "6e81b90e": [
      19
    ],
    "28b2e440": [
      19
    ],
    "5e6b399d": [
      19
    ],
    "7fb24a98": [
      19
    ],
    "450750f4": [
      19
    ],
    "77c8a08e": [
      19
    ],
    "0ffcfbf8": [
      19
    ],
    "6f77db7c": [
      19
    ],
    "237ede77": [
      19
    ],
    "60bc3fc2": [
      19
    ],
    "721ec83b": [
      19
    ],
    "e6b8dd98": [
      19
    ],
    "5ea1c625": [
      19
    ],
    "8d8c396e": [
      19
    ],
    "015bf366": [
      19
    ],
    "832754a6": [
      19
    ],
    "e3240086": [
      19
    ],
    "5b15c33e": [
      19
    ],
    "4bb0928f": [
      3
    ],
    "67ad7348": [
      14
    ],
    "5d95cb50": [
      14
    ],
    "502e2a97": [
      15,
      32
    ],
    "6bad810c": [
      15,
      32
    ],
    "576fa243": [
      15,
      32
    ],
    "9068ac16": [
      15,
      32
    ],
    "0b8c3017": [
      15,
      32
    ],
    "18296fea": [
      15,
      32
    ],
    "5f9bf706": [
      5
    ],
    "481f0526": [
      5
    ],
    "0edce2f9": [
      5
    ],
    "490e17c2": [
      8,
      32,
      30
    ],
    "1ea3feaa": [
      8,
      32,
      30
    ],
    "2a64cc3b": [
      3
    ],
    "62061fb6": [
      3
    ],
    "049ef682": [
      3
    ],
    "8aa3b0ea": [
      3
    ],
    "258d275d": [
      3
    ],
    "5ce307c8": [
      3
    ],
    "5a59730c": [
      2
    ],
    "bfcf00a8": [
      2
    ],
    "97febfe4": [
      2
    ],
    "57f39412": [
      2
    ],
    "e87e7ea8": [
      2
    ],
    "edff89b4": [
      13
    ],
    "1af4c722": [
      13
    ],
    "251d4934": [
      13
    ],
    "ab3e9e56": [
      13
    ],
    "06452c5c": [
      13
    ],
    "2d25bcdc": [
      4,
      32,
      34,
      31,
      30
    ],
    "6aa2f29c": [
      4,
      32,
      34,
      31,
      30
    ],
    "6194f308": [
      4,
      32,
      34,
      31,
      30
    ],
    "cfeaf4fc": [
      4,
      32,
      34,
      31,
      30
    ],
    "49cf6426": [
      4,
      32,
      34,
      31,
      30
    ],
    "61421be8": [
      23
    ],
    "df55269c": [
      23
    ],
    "112f329c": [
      23
    ],
    "61aef160": [
      23
    ],
    "556892ed": [
      26
    ],
    "215eedd7": [
      26
    ],
    "3606b57a": [
      26
    ],
    "64e66631": [
      26
    ],
    "05409865": [
      26
    ],
    "748cfbd9": [
      22
    ],
    "862c6da2": [
      22
    ],
    "ad938dbe": [
      22
    ],
    "fdaa81d6": [
      22
    ],
    "65bc2d82": [
      22
    ],
    "56ef77ee": [
      11
    ],
    "2482568a": [
      11
    ],
    "d1967b32": [
      11
    ],
    "2486dad6": [
      11
    ],
    "1e81d3ee": [
      11
    ],
    "19d376f8": [
      9
    ],
    "363ec64a": [
      9
    ],
    "e7fc2650": [
      9
    ],
    "946cdfb8": [
      9
    ],
    "a9d4c10c": [
      9
    ],
    "50e11908": [
      12
    ],
    "15b5715c": [
      12
    ],
    "2a4fe110": [
      12
    ],
    "cf388b20": [
      12
    ],
    "3bcc989e": [
      14
    ],
    "c92c1044": [
      14
    ],
    "4973c089": [
      14
    ],
    "0d386944": [
      14
    ],
    "0cd66227": [
      14
    ],
    "1b8ae6c0": [
      15,
      32
    ],
    "09d219ca": [
      15,
      32
    ],
    "75383d8c": [
      15,
      32
    ],
    "330ea301": [
      15,
      32
    ],
    "3aa49358": [
      15,
      32
    ],
    "7e621abf": [
      5
    ],
    "3da337ab": [
      5
    ],
    "56ade99e": [
      5
    ],
    "6fce25f6": [
      5
    ],
    "22d0415a": [
      5
    ],
    "bb3afb78": [
      17
    ],
    "48367c2c": [
      17
    ],
    "02f142d4": [
      17
    ],
    "094c54d0": [
      17
    ],
    "327c6098": [
      17
    ],
    "ab6d7c26": [
      8,
      32,
      30
    ],
    "16d3ce7e": [
      8,
      32,
      30
    ],
    "39bfef83": [
      8,
      32,
      30
    ],
    "7420e29b": [
      8,
      32,
      30
    ],
    "58d3a225": [
      8,
      32,
      30
    ]
  },
  "assetsMapping": {
    "311a2d4d599f7e5bd790.js": "16774e62",
    "32ded5284d79f4a35aad.js": "4347167e",
    "4187cdb5398fac9d25e2.js": "427a0f95",
    "41dccc96d2d7a4fd1668.js": "06ad6b2c",
    "4e4d0387b71b4539c23b.js": "1a3ae26b",
    "5407908505dbb02560d9.js": "103b25c2",
    "560418cb4ead47a50d1e.js": "715a3ccc",
    "5c35d50e9d12c2981651.js": "7ebf5425",
    "62bcf57db8e17331dc63.js": "6fca0322",
    "6f968b45647b6e02592b.js": "1807fc36",
    "7b83f8f0816d35e415de.js": "77fc670b",
    "8cd23b5b8c49f27bb6eb.js": "6ff73de9",
    "8d706debddaf91c0a0e0.js": "39540e74",
    "8f4585846ca3b6117762.js": "08ac27ba",
    "904bf52b613d7359f3f6.js": "7258217e",
    "99237e4ac0fae07266f0.js": "0ce0cd72",
    "a8a28637501f4f351239.js": "304b3202",
    "cfb56d17c63f08d6ea3e.js": "7ea1d828",
    "d1dab072b03d17a303e2.js": "0859c165",
    "d269f45e02ab5a7ccae6.js": "f71faa48",
    "f0300d3cb3f5e5f98bcc.js": "043bcfab",
    "f8649136fdec279fde4a.js": "121ff01d",
    "fcd9def8c6eacbe703b3.js": "3e2c8d60",
    "fe7b3f56b0d0d23ea531.js": "729c404c"
  }
}